kombu_batteries_included/__init__.py
kombu_batteries_included/config.py
kombu_batteries_included/infra.py
kombu_batteries_included/py.typed
kombu_batteries_included-1.1.4.dist-info/LICENSE.md
kombu_batteries_included-1.1.4.dist-info/WHEEL
kombu_batteries_included-1.1.4.dist-info/METADATA
kombu_batteries_included-1.1.4.dist-info/RECORD
